Workbook

Sheet Assumptions
C3: Select case | D3: 2
C4: Downside | D4: 1
C5: Base | D5: 2
C6: Upside | D6: 3
B8: Multiplier | C8: Assumptions | D8: 2021 | E8: =D8+1 -> 2022 | F8: =E8+1 -> 2023 | G8: =F8+1 -> 2024 | H8: =G8+1 -> 2025 | I8: =H8+1 -> 2026 | J8: =I8+1 -> 2027 | K8: =J8+1 -> 2028 | L8: =K8+1 -> 2029 | M8: =L8+1 -> 2030
C10: Revenue:
C11: Online store growth
C12: =OFFSET(C12,$D$3,0) -> Base | I12: =OFFSET(I12,$D$3,0) -> 0.075 | J12: =OFFSET(J12,$D$3,0) -> 0.0702 | K12: =OFFSET(K12,$D$3,0) -> 0.0696 | L12: =OFFSET(L12,$D$3,0) -> 0.0729 | M12: =OFFSET(M12,$D$3,0) -> 0.0716
B13: 0.5 | C13: Downside | I13: =I14*$B13 -> 0.0375 | J13: =J14*$B13 -> 0.0351 | K13: =K14*$B13 -> 0.0348 | L13: =L14*$B13 -> 0.03645 | M13: =M14*$B13 -> 0.0358 | N13: Macro slowdown + tariff drag on consumer discretionary. Retail growth was already single digits and Amazon themselves guided only 7-11% total revenue growth.
C14: Base | E14: ='FCF Components'!D8 -> -0.0093256783 | F14: ='FCF Components'!E8 -> 0.053944474 | G14: ='FCF Components'!F8 -> 0.065367962 | H14: ='FCF Components'!G8 -> 0.090102781 | I14: 0.075 | J14: 0.0702 | K14: 0.0696 | L14: 0.0729 | M14: 0.0716
B15: 1.35 | C15: Upside | I15: =I14*$B15 -> 0.10125 | J15: =J14*$B15 -> 0.09477 | K15: =K14*$B15 -> 0.09396 | L15: =L14*$B15 -> 0.098415 | M15: =M14*$B15 -> 0.09666 | N15: Same-day delivery expansion beyond 2,300 communities, AI-driven personalization lift, and market share gains from weaker competitors
C17: Physical stores growth
C18: =OFFSET(C18,$D$3,0) -> Base | I18: =OFFSET(I18,$D$3,0) -> 0.0507 | J18: =OFFSET(J18,$D$3,0) -> 0.05 | K18: =OFFSET(K18,$D$3,0) -> 0.0448 | L18: =OFFSET(L18,$D$3,0) -> 0.0432 | M18: =OFFSET(M18,$D$3,0) -> 0.0416
B19: 0.4 | C19: Downside | I19: =I20*$B19 -> 0.02028 | J19: =J20*$B19 -> 0.02 | K19: =K20*$B19 -> 0.01792 | L19: =L20*$B19 -> 0.01728 | M19: =M20*$B19 -> 0.01664 | N19: Whole Foods has seen limited expansion and Amazon Fresh closures signal strategic deprioritization.
C20: Base | E20: ='FCF Components'!D11 -> 0.11057101 | F20: ='FCF Components'!E11 -> 0.056267468 | G20: ='FCF Components'!F11 -> 0.059161258 | H20: ='FCF Components'!G11 -> 0.063445675 | I20: 0.0507 | J20: 0.05 | K20: 0.0448 | L20: 0.0432 | M20: 0.0416
B21: 1.4 | C21: Upside | I21: =I20*$B21 -> 0.07098 | J21: =J20*$B21 -> 0.07 | K21: =K20*$B21 -> 0.06272 | L21: =L20*$B21 -> 0.06048 | M21: =M20*$B21 -> 0.05824 | N21: Amazon One/Just Walk Out tech rollout + grocery automation. Note that physical retail isn't a strategic priority.
C23: Third-party seller services growth
C24: =OFFSET(C24,$D$3,0) -> Base | I24: =OFFSET(I24,$D$3,0) -> 0.1054 | J24: =OFFSET(J24,$D$3,0) -> 0.09 | K24: =OFFSET(K24,$D$3,0) -> 0.0954 | L24: =OFFSET(L24,$D$3,0) -> 0.0893 | M24: =OFFSET(M24,$D$3,0) -> 0.0833
B25: 0.65 | C25: Downside | I25: =I26*$B25 -> 0.06851 | J25: =J26*$B25 -> 0.0585 | K25: =K26*$B25 -> 0.06201 | L25: =L26*$B25 -> 0.058045 | M25: =M26*$B25 -> 0.054145 | N25: FTC Antitrust Trial could reduce margins
C26: Base | E26: ='FCF Components'!D14 -> 0.13882708 | F26: ='FCF Components'!E14 -> 0.1897533 | G26: ='FCF Components'!F14 -> 0.1149065 | H26: ='FCF Components'!G14 -> 0.10257067 | I26: 0.1054 | J26: 0.09 | K26: 0.0954 | L26: 0.0893 | M26: 0.0833
B27: 1.25 | C27: Upside | I27: =I26*$B27 -> 0.13175 | J27: =J26*$B27 -> 0.1125 | K27: =K26*$B27 -> 0.11925 | L27: =L26*$B27 -> 0.111625 | M27: =M26*$B27 -> 0.104125 | N27: Buy with Prime expansion off-Amazon, Multi-channel fulfillment opening to larger sellers (Walmart, Shopify)
C29: Advertising services growth
C30: =OFFSET(C30,$D$3,0) -> Base | I30: =OFFSET(I30,$D$3,0) -> 0.1845 | J30: =OFFSET(J30,$D$3,0) -> 0.1727 | K30: =OFFSET(K30,$D$3,0) -> 0.1519 | L30: =OFFSET(L30,$D$3,0) -> 0.1389 | M30: =OFFSET(M30,$D$3,0) -> 0.1303
B31: 0.7 | C31: Downside | I31: =I32*$B31 -> 0.12915 | J31: =J32*$B31 -> 0.12089 | K31: =K32*$B31 -> 0.10633 | L31: =L32*$B31 -> 0.09723 | M31: =M32*$B31 -> 0.09121 | N31: Consumer spending pullback or recession fears reduce ad growth.
C32: Base | E32: ='FCF Components'!D17 -> 0.21113607 | F32: ='FCF Components'!E17 -> 0.24290522 | G32: ='FCF Components'!F17 -> 0.19843943 | H32: ='FCF Components'!G17 -> 0.22095919 | I32: 0.1845 | J32: 0.1727 | K32: 0.1519 | L32: 0.1389 | M32: 0.1303
B33: 1.3 | C33: Upside | I33: =I32*$B33 -> 0.23985 | J33: =J32*$B33 -> 0.22451 | K33: =K32*$B33 -> 0.19747 | L33: =L32*$B33 -> 0.18057 | M33: =M32*$B33 -> 0.16939 | N33: Prime Video ad tiers grow, enhanced ad management across Prime Video, Twitch, Fire TV and third party sites/apps
C35: Subscription services growth
C36: =OFFSET(C36,$D$3,0) -> Base | I36: =OFFSET(I36,$D$3,0) -> 0.1034 | J36: =OFFSET(J36,$D$3,0) -> 0.0968 | K36: =OFFSET(K36,$D$3,0) -> 0.0898 | L36: =OFFSET(L36,$D$3,0) -> 0.0827 | M36: =OFFSET(M36,$D$3,0) -> 0.0792
B37: 0.7 | C37: Downside | I37: =I38*$B37 -> 0.07238 | J37: =J38*$B37 -> 0.06776 | K37: =K38*$B37 -> 0.06286 | L37: =L38*$B37 -> 0.05789 | M37: =M38*$B37 -> 0.05544 | N37: Prime subscriber growth slows down in developed markets
C38: Base | E38: ='FCF Components'!D20 -> 0.10859985 | F38: ='FCF Components'!E20 -> 0.1417173 | G38: ='FCF Components'!F20 -> 0.10358377 | H38: ='FCF Components'!G20 -> 0.11819985 | I38: 0.1034 | J38: 0.0968 | K38: 0.0898 | L38: 0.0827 | M38: 0.0792
B39: 1.3 | C39: Upside | I39: =I38*$B39 -> 0.13442 | J39: =J38*$B39 -> 0.12584 | K39: =K38*$B39 -> 0.11674 | L39: =L38*$B39 -> 0.10751 | M39: =M38*$B39 -> 0.10296 | N39: Prime keeps its competitive moat and expands into other segments like pharmacy, making attractive bundles
C41: AWS growth
C42: =OFFSET(C42,$D$3,0) -> Base | I42: =OFFSET(I42,$D$3,0) -> 0.2443 | J42: =OFFSET(J42,$D$3,0) -> 0.2289 | K42: =OFFSET(K42,$D$3,0) -> 0.2241 | L42: =OFFSET(L42,$D$3,0) -> 0.1869 | M42: =OFFSET(M42,$D$3,0) -> 0.1689
B43: 0.75 | C43: Downside | I43: =I44*$B43 -> 0.183225 | J43: =J44*$B43 -> 0.171675 | K43: =K44*$B43 -> 0.168075 | L43: =L44*$B43 -> 0.140175 | M43: =M44*$B43 -> 0.126675 | N43: Azure/GCP share increases, AI capex cycle peaks.
C44: Base | E44: ='FCF Components'!D23 -> 0.28767564 | F44: ='FCF Components'!E23 -> 0.13310278 | G44: ='FCF Components'!F23 -> 0.18509867 | H44: ='FCF Components'!G23 -> 0.1968184 | I44: 0.2443 | J44: 0.2289 | K44: 0.2241 | L44: 0.1869 | M44: 0.1689
B45: 1.15 | C45: Upside | I45: =I44*$B45 -> 0.280945 | J45: =J44*$B45 -> 0.263235 | K45: =K44*$B45 -> 0.257715 | L45: =L44*$B45 -> 0.214935 | M45: =M44*$B45 -> 0.194235 | N45: AI workload accelerates, Trainium adoption beyond Anthropic
C47: Other growth
C48: =OFFSET(C48,$D$3,0) -> Base | I48: =OFFSET(I48,$D$3,0) -> 0.04 | J48: =OFFSET(J48,$D$3,0) -> 0.04 | K48: =OFFSET(K48,$D$3,0) -> 0.04 | L48: =OFFSET(L48,$D$3,0) -> 0.04 | M48: =OFFSET(M48,$D$3,0) -> 0.04
B49: 0.9 | C49: Downside | I49: =I50*$B49 -> 0.036 | J49: =J50*$B49 -> 0.036 | K49: =K50*$B49 -> 0.036 | L49: =L50*$B49 -> 0.036 | M49: =M50*$B49 -> 0.036 | N49: Uncertainty around Kuiper, etc
C50: Base | E50: ='FCF Components'!D26 -> 0 | F50: ='FCF Components'!E26 -> 0.16741229 | G50: ='FCF Components'!F26 -> 0.094191206 | H50: ='FCF Components'!G26 -> 0.094009217 | I50: 0.04 | J50: 0.04 | K50: 0.04 | L50: 0.04 | M50: 0.04
B51: 2.5 | C51: Upside | I51: =I50*$B51 -> 0.1 | J51: =J50*$B51 -> 0.1 | K51: =K50*$B51 -> 0.1 | L51: =L50*$B51 -> 0.1 | M51: =M50*$B51 -> 0.1 | N51: Kuiper satellite launches begin commercial service, other ambitious projects start contributing
C53: Fulfillment expense - % of total revenue
C54: =OFFSET(C54,$D$3,0) -> Base | I54: =OFFSET(I54,$D$3,0) -> 0.15208967 | J54: =OFFSET(J54,$D$3,0) -> 0.14944661 | K54: =OFFSET(K54,$D$3,0) -> 0.14643674 | L54: =OFFSET(L54,$D$3,0) -> 0.14185474 | M54: =OFFSET(M54,$D$3,0) -> 0.13765687
B55: 1.05 | C55: Downside | I55: =I56*$B55 -> 0.15969416 | J55: =J56*$B55 -> 0.15691894 | K55: =K56*$B55 -> 0.15375858 | L55: =L56*$B55 -> 0.14894748 | M55: =M56*$B55 -> 0.14453971
C56: Base | D56: ='FCF Components'!C37/'FCF Components'!C28 -> 0.15987119 | E56: ='FCF Components'!D37/'FCF Components'!D28 -> 0.16401126 | F56: ='FCF Components'!E37/'FCF Components'!E28 -> 0.15765721 | G56: ='FCF Components'!F37/'FCF Components'!F28 -> 0.15440647 | H56: ='FCF Components'!G37/'FCF Components'!G28 -> 0.15214165 | I56: 0.15208967 | J56: 0.14944661 | K56: 0.14643674 | L56: 0.14185474 | M56: 0.13765687
B57: 0.95 | C57: Upside | I57: =I56*$B57 -> 0.14448519 | J57: =J56*$B57 -> 0.14197428 | K57: =K56*$B57 -> 0.13911491 | L57: =L56*$B57 -> 0.13476201 | M57: =M56*$B57 -> 0.13077403
C59: Tech and infrastructure expense - % of total revenue
C60: =OFFSET(C60,$D$3,0) -> Base | I60: =OFFSET(I60,$D$3,0) -> 0.1571 | J60: =OFFSET(J60,$D$3,0) -> 0.1598 | K60: =OFFSET(K60,$D$3,0) -> 0.1663 | L60: =OFFSET(L60,$D$3,0) -> 0.1698 | M60: =OFFSET(M60,$D$3,0) -> 0.1706
B61: 1.05 | C61: Downside | I61: =I62*$B61 -> 0.164955 | J61: =J62*$B61 -> 0.16779 | K61: =K62*$B61 -> 0.174615 | L61: =L62*$B61 -> 0.17829 | M61: =M62*$B61 -> 0.17913
C62: Base | D62: ='FCF Components'!C38/'FCF Components'!C28 -> 0.11930476 | E62: ='FCF Components'!D38/'FCF Components'!D28 -> 0.14244245 | F62: ='FCF Components'!E38/'FCF Components'!E28 -> 0.14896353 | G62: ='FCF Components'!F38/'FCF Components'!F28 -> 0.13879262 | H62: ='FCF Components'!G38/'FCF Components'!G28 -> 0.1513703 | I62: 0.1571 | J62: 0.1598 | K62: 0.1663 | L62: 0.1698 | M62: 0.1706
B63: 0.95 | C63: Upside | I63: =I62*$B63 -> 0.149245 | J63: =J62*$B63 -> 0.15181 | K63: =K62*$B63 -> 0.157985 | L63: =L62*$B63 -> 0.16131 | M63: =M62*$B63 -> 0.16207
C65: Sales and marketing - % of total revenue
C66: =OFFSET(C66,$D$3,0) -> Base | I66: =OFFSET(I66,$D$3,0) -> 0.0651 | J66: =OFFSET(J66,$D$3,0) -> 0.0645 | K66: =OFFSET(K66,$D$3,0) -> 0.0627 | L66: =OFFSET(L66,$D$3,0) -> 0.0607 | M66: =OFFSET(M66,$D$3,0) -> 0.0592
B67: 1.05 | C67: Downside | I67: =I68*$B67 -> 0.068355 | J67: =J68*$B67 -> 0.067725 | K67: =K68*$B67 -> 0.065835 | L67: =L68*$B67 -> 0.063735 | M67: =M68*$B67 -> 0.06216
C68: Base | D68: ='FCF Components'!C39/'FCF Components'!C28 -> 0.069283686 | E68: ='FCF Components'!D39/'FCF Components'!D28 -> 0.082177815 | F68: ='FCF Components'!E39/'FCF Components'!E28 -> 0.077194081 | G68: ='FCF Components'!F39/'FCF Components'!F28 -> 0.068824172 | H68: ='FCF Components'!G39/'FCF Components'!G28 -> 0.065737791 | I68: 0.0651 | J68: 0.0645 | K68: 0.0627 | L68: 0.0607 | M68: 0.0592
B69: 0.95 | C69: Upside | I69: =I68*$B69 -> 0.061845 | J69: =J68*$B69 -> 0.061275 | K69: =K68*$B69 -> 0.059565 | L69: =L68*$B69 -> 0.057665 | M69: =M68*$B69 -> 0.05624
C71: General and administrative - % of total revenue
C72: =OFFSET(C72,$D$3,0) -> Base | I72: =OFFSET(I72,$D$3,0) -> 0.0156 | J72: =OFFSET(J72,$D$3,0) -> 0.016 | K72: =OFFSET(K72,$D$3,0) -> 0.0148 | L72: =OFFSET(L72,$D$3,0) -> 0.0138 | M72: =OFFSET(M72,$D$3,0) -> 0.0131
B73: 1.1 | C73: Downside | I73: =I74*$B73 -> 0.01716 | J73: =J74*$B73 -> 0.0176 | K73: =K74*$B73 -> 0.01628 | L73: =L74*$B73 -> 0.01518 | M73: =M74*$B73 -> 0.01441
C74: Base | D74: ='FCF Components'!C40/'FCF Components'!C28 -> 0.018779453 | E74: ='FCF Components'!D40/'FCF Components'!D28 -> 0.023135006 | F74: ='FCF Components'!E40/'FCF Components'!E28 -> 0.020557252 | G74: ='FCF Components'!F40/'FCF Components'!F28 -> 0.017805219 | H74: ='FCF Components'!G40/'FCF Components'!G28 -> 0.015583242 | I74: 0.0156 | J74: 0.016 | K74: 0.0148 | L74: 0.0138 | M74: 0.0131
B75: 0.9 | C75: Upside | I75: =I74*$B75 -> 0.01404 | J75: =J74*$B75 -> 0.0144 | K75: =K74*$B75 -> 0.01332 | L75: =L74*$B75 -> 0.01242 | M75: =M74*$B75 -> 0.01179
C77: Other expenses - % of total revenue
C78: =OFFSET(C78,$D$3,0) -> Base | I78: =OFFSET(I78,$D$3,0) -> 0.0019144868 | J78: =OFFSET(J78,$D$3,0) -> 0.0018627752 | K78: =OFFSET(K78,$D$3,0) -> 0.002005042 | L78: =OFFSET(L78,$D$3,0) -> 0.0020336231 | M78: =OFFSET(M78,$D$3,0) -> 0.002
B79: 1.5 | C79: Downside | I79: =I80*$B79 -> 0.0028717302 | J79: =J80*$B79 -> 0.0027941628 | K79: =K80*$B79 -> 0.003007563 | L79: =L80*$B79 -> 0.0030504346 | M79: =M80*$B79 -> 0.003
C80: Base | D80: ='FCF Components'!C41/'FCF Components'!C28 -> 0.00013196487 | E80: ='FCF Components'!D41/'FCF Components'!D28 -> 0.0024572797 | F80: ='FCF Components'!E41/'FCF Components'!E28 -> 0.001334412 | G80: ='FCF Components'!F41/'FCF Components'!F28 -> 0.0011960016 | H80: ='FCF Components'!G41/'FCF Components'!G28 -> 0.0064706998 | I80: 0.0019144868 | J80: 0.0018627752 | K80: 0.002005042 | L80: 0.0020336231 | M80: 0.002
B81: 0.75 | C81: Upside | I81: =I80*$B81 -> 0.0014358651 | J81: =J80*$B81 -> 0.0013970814 | K81: =K80*$B81 -> 0.0015037815 | L81: =L80*$B81 -> 0.0015252173 | M81: =M80*$B81 -> 0.0015
C83: Cost of sales - % of total revenue
C84: =OFFSET(C84,$D$3,0) -> Base | I84: =OFFSET(I84,$D$3,0) -> 0.491 | J84: =OFFSET(J84,$D$3,0) -> 0.4795 | K84: =OFFSET(K84,$D$3,0) -> 0.4615 | L84: =OFFSET(L84,$D$3,0) -> 0.4582 | M84: =OFFSET(M84,$D$3,0) -> 0.4478
B85: 1.05 | C85: Downside | I85: =I86*$B85 -> 0.51555 | J85: =J86*$B85 -> 0.503475 | K85: =K86*$B85 -> 0.484575 | L85: =L86*$B85 -> 0.48111 | M85: =M86*$B85 -> 0.47019
C86: Base | D86: ='FCF Components'!C32 -> 0.57967486 | E86: ='FCF Components'!D32 -> 0.5619466 | F86: ='FCF Components'!E32 -> 0.53017911 | G86: ='FCF Components'!F32 -> 0.51145607 | H86: ='FCF Components'!G32 -> 0.49714335 | I86: 0.491 | J86: 0.4795 | K86: 0.4615 | L86: 0.4582 | M86: 0.4478
B87: 0.95 | C87: Upside | I87: =I86*$B87 -> 0.46645 | J87: =J86*$B87 -> 0.455525 | K87: =K86*$B87 -> 0.438425 | L87: =L86*$B87 -> 0.43529 | M87: =M86*$B87 -> 0.42541
C89: Tax rate
C90: =OFFSET(C90,$D$3,0) -> Base | I90: =OFFSET(I90,$D$3,0) -> 0.1819 | J90: =OFFSET(J90,$D$3,0) -> 0.1812 | K90: =OFFSET(K90,$D$3,0) -> 0.1829 | L90: =OFFSET(L90,$D$3,0) -> 0.1806 | M90: =OFFSET(M90,$D$3,0) -> 0.1806
B91: 1.1 | C91: Downside | I91: =I92*$B91 -> 0.20009 | J91: =J92*$B91 -> 0.19932 | K91: =K92*$B91 -> 0.20119 | L91: =L92*$B91 -> 0.19866 | M91: =M92*$B91 -> 0.19866
C92: Base | D92: ='FCF Components'!C52/'FCF Components'!C51 -> 0.12558322 | E92: ='FCF Components'!D52/'FCF Components'!D51 -> 0.54194744 | F92: ='FCF Components'!E52/'FCF Components'!E51 -> 0.18957851 | G92: ='FCF Components'!F52/'FCF Components'!F51 -> 0.13503075 | H92: ='FCF Components'!G52/'FCF Components'!G51 -> 0.19614432 | I92: 0.1819 | J92: 0.1812 | K92: 0.1829 | L92: 0.1806 | M92: 0.1806
B93: 0.9 | C93: Upside | I93: =I92*$B93 -> 0.16371 | J93: =J92*$B93 -> 0.16308 | K93: =K92*$B93 -> 0.16461 | L93: =L92*$B93 -> 0.16254 | M93: =M92*$B93 -> 0.16254
C95: Capital expenditures - % of total revenue
C96: Base | I96: 0 | J96: 0 | K96: 0 | L96: 0 | M96: 0
B97: 1.15 | C97: Downside | I97: =I98*$B97 -> 0.276 | J97: =J98*$B97 -> 0.23 | K97: =K98*$B97 -> 0.207 | L97: =L98*$B97 -> 0.1725 | M97: =M98*$B97 -> 0.1725
C98: Base | D98: ='FCF Components'!C62/'FCF Components'!C28 -> 0.11790848 | E98: ='FCF Components'!D62/'FCF Components'!D28 -> 0.11346873 | F98: ='FCF Components'!E62/'FCF Components'!E28 -> 0.083740877 | G98: ='FCF Components'!F62/'FCF Components'!F28 -> 0.12172883 | H98: ='FCF Components'!G62/'FCF Components'!G28 -> 0.17898689 | I98: 0.24 | J98: 0.2 | K98: 0.18 | L98: 0.15 | M98: 0.15
B99: 0.8 | C99: Upside | I99: =I98*$B99 -> 0.192 | J99: =J98*$B99 -> 0.16 | K99: =K98*$B99 -> 0.144 | L99: =L98*$B99 -> 0.12 | M99: =M98*$B99 -> 0.12
C101: Accumulated depreciation - % of gross property and equipment
C102: Base | I102: 0 | J102: 0 | K102: 0 | L102: 0 | M102: 0
B103: 1.05 | C103: Downside | I103: =I104*$B103 -> 0.3675 | J103: =J104*$B103 -> 0.3675 | K103: =K104*$B103 -> 0.3675 | L103: =L104*$B103 -> 0.3675 | M103: =M104*$B103 -> 0.3675
C104: Base | D104: ='FCF Components'!C59/'FCF Components'!C58 -> 0.32880653 | E104: ='FCF Components'!D59/'FCF Components'!D58 -> 0.34192718 | F104: ='FCF Components'!E59/'FCF Components'!E58 -> 0.37038373 | G104: ='FCF Components'!F59/'FCF Components'!F58 -> 0.35880778 | H104: ='FCF Components'!G59/'FCF Components'!G58 -> 0.33153653 | I104: 0.35 | J104: 0.35 | K104: 0.35 | L104: 0.35 | M104: 0.35
B105: 0.95 | C105: Upside | I105: =I104*$B105 -> 0.3325 | J105: =J104*$B105 -> 0.3325 | K105: =K104*$B105 -> 0.3325 | L105: =L104*$B105 -> 0.3325 | M105: =M104*$B105 -> 0.3325
C107: Accounts receivable - % of total revenue
C108: Base | I108: 0 | J108: 0 | K108: 0 | L108: 0 | M108: 0
B109: 1.05 | C109: Downside | I109: =I110*$B109 -> 0.096915 | J109: =J110*$B109 -> 0.096075 | K109: =K110*$B109 -> 0.09912 | L109: =L110*$B109 -> 0.0945 | M109: =M110*$B109 -> 0.09345
C110: Base | D110: ='FCF Components'!C72/'FCF Components'!C28 -> 0.070007364 | E110: ='FCF Components'!D72/'FCF Components'!D28 -> 0.082415177 | F110: ='FCF Components'!E72/'FCF Components'!E28 -> 0.090908775 | G110: ='FCF Components'!F72/'FCF Components'!F28 -> 0.086919379 | H110: ='FCF Components'!G72/'FCF Components'!G28 -> 0.094471659 | I110: 0.0923 | J110: 0.0915 | K110: 0.0944 | L110: 0.09 | M110: 0.089
B111: 0.95 | C111: Upside | H111: 0.0535 | I111: =I110*$B111 -> 0.087685 | J111: =J110*$B111 -> 0.086925 | K111: =K110*$B111 -> 0.08968 | L111: =L110*$B111 -> 0.0855 | M111: =M110*$B111 -> 0.08455
C113: Inventories - % of total revenue
C114: Base | I114: 0 | J114: 0 | K114: 0 | L114: 0 | M114: 0
B115: 1.05 | C115: Downside | I115: =I116*$B115 -> 0.055545 | J115: =J116*$B115 -> 0.053865 | K115: =K116*$B115 -> 0.052815 | L115: =L116*$B115 -> 0.05145 | M115: =M116*$B115 -> 0.05019
C116: Base | D116: ='FCF Components'!C73/'FCF Components'!C28 -> 0.06947312 | E116: ='FCF Components'!D73/'FCF Components'!D28 -> 0.066938012 | F116: ='FCF Components'!E73/'FCF Components'!E28 -> 0.057966022 | G116: ='FCF Components'!F73/'FCF Components'!F28 -> 0.053630406 | H116: ='FCF Components'!G73/'FCF Components'!G28 -> 0.053457549 | I116: 0.0529 | J116: 0.0513 | K116: 0.0503 | L116: 0.049 | M116: 0.0478
B117: 0.95 | C117: Upside | I117: =I116*$B117 -> 0.050255 | J117: =J116*$B117 -> 0.048735 | K117: =K116*$B117 -> 0.047785 | L117: =L116*$B117 -> 0.04655 | M117: =M116*$B117 -> 0.04541
C119: Accounts payable - % of operating expenses
C120: Base | I120: 0 | J120: 0 | K120: 0 | L120: 0 | M120: 0
B121: 0.95 | C121: Downside | I121: =I122*$B121 -> 0.370405 | J121: =J122*$B121 -> 0.35834 | K121: =K122*$B121 -> 0.326515 | L121: =L122*$B121 -> 0.33364 | M121: =M122*$B121 -> 0.32509
C122: Base | D122: ='FCF Components'!C78/'FCF Components'!C43 -> 0.45576162 | E122: ='FCF Components'!D78/'FCF Components'!D43 -> 0.37387743 | F122: ='FCF Components'!E78/'FCF Components'!E43 -> 0.36403595 | G122: ='FCF Components'!F78/'FCF Components'!F43 -> 0.3882005 | H122: ='FCF Components'!G78/'FCF Components'!G43 -> 0.43455897 | I122: 0.3899 | J122: 0.3772 | K122: 0.3437 | L122: 0.3512 | M122: 0.3422
...

Sheet FCF Components
L1: ="CURRENTLY VIEWING "&CHOOSE(Assumptions!$D$3,"DOWNSIDE","BASE","UPSIDE")&" CASE" -> CURRENTLY VIEWING BASE CASE
B2: Free Cash Flow Components | C2: Actual | H2: Expected
B3: USD ($) in millions | C3: 2021 | D3: =C3+1 -> 2022 | E3: =D3+1 -> 2023 | F3: =E3+1 -> 2024 | G3: =F3+1 -> 2025 | H3: =G3+1 -> 2026 | I3: =H3+1 -> 2027 | J3: =I3+1 -> 2028 | K3: =J3+1 -> 2029 | L3: =K3+1 -> 2030
B4: Income Statement:
B5: Revenues
B7: Online stores | C7: 222075 | D7: 220004 | E7: 231872 | F7: 247029 | G7: 269287 | H7: =G7*(1+Assumptions!I14) -> 289483.52 | I7: =H7*(1+Assumptions!J14) -> 309805.27 | J7: =I7*(1+Assumptions!K14) -> 331367.72 | K7: =J7*(1+Assumptions!L14) -> 355524.42 | L7: =K7*(1+Assumptions!M14) -> 380979.97
B8: Online stores growth | D8: =D7/C7-1 -> -0.0093256783 | E8: =E7/D7-1 -> 0.053944474 | F8: =F7/E7-1 -> 0.065367962 | G8: =G7/F7-1 -> 0.090102781 | H8: =Assumptions!I12 -> 0.075 | I8: =Assumptions!J12 -> 0.0702 | J8: =Assumptions!K12 -> 0.0696 | K8: =Assumptions!L12 -> 0.0729 | L8: =Assumptions!M12 -> 0.0716
B10: Physical stores | C10: 17075 | D10: 18963 | E10: 20030 | F10: 21215 | G10: 22561 | H10: =G10*(1+Assumptions!I20) -> 23704.843 | I10: =H10*(1+I11) -> 24890.085 | J10: =I10*(1+J11) -> 26005.161 | K10: =J10*(1+K11) -> 27128.584 | L10: =K10*(1+L11) -> 28257.133
B11: Physical stores growth | D11: =D10/C10-1 -> 0.11057101 | E11: =E10/D10-1 -> 0.056267468 | F11: =F10/E10-1 -> 0.059161258 | G11: =G10/F10-1 -> 0.063445675 | H11: =Assumptions!I18 -> 0.0507 | I11: =Assumptions!J18 -> 0.05 | J11: =Assumptions!K18 -> 0.0448 | K11: =Assumptions!L18 -> 0.0432 | L11: =Assumptions!M18 -> 0.0416
B13: Third-party seller services | C13: 103366 | D13: 117716 | E13: 140053 | F13: 156146 | G13: 172162 | H13: =G13*(1+Assumptions!I26) -> 190307.87 | I13: =H13*(1+I14) -> 207435.58 | J13: =I13*(1+J14) -> 227224.94 | K13: =J13*(1+K14) -> 247516.13 | L13: =K13*(1+L14) -> 268134.22
B14: Third-party seller services growth | D14: =D13/C13-1 -> 0.13882708 | E14: =E13/D13-1 -> 0.1897533 | F14: =F13/E13-1 -> 0.1149065 | G14: =G13/F13-1 -> 0.10257067 | H14: =Assumptions!I24 -> 0.1054 | I14: =Assumptions!J24 -> 0.09 | J14: =Assumptions!K24 -> 0.0954 | K14: =Assumptions!L24 -> 0.0893 | L14: =Assumptions!M24 -> 0.0833
B16: Advertising services | C16: 31160 | D16: 37739 | E16: 46906 | F16: 56214 | G16: 68635 | H16: =G16*(1+Assumptions!I32) -> 81298.157 | I16: =H16*(1+I17) -> 95338.349 | J16: =I16*(1+J17) -> 109820.24 | K16: =J16*(1+K17) -> 125074.28 | L16: =K16*(1+L17) -> 141371.45
B17: Advertising services growth | D17: =D16/C16-1 -> 0.21113607 | E17: =E16/D16-1 -> 0.24290522 | F17: =F16/E16-1 -> 0.19843943 | G17: =G16/F16-1 -> 0.22095919 | H17: =Assumptions!I30 -> 0.1845 | I17: =Assumptions!J30 -> 0.1727 | J17: =Assumptions!K30 -> 0.1519 | K17: =Assumptions!L30 -> 0.1389 | L17: =Assumptions!M30 -> 0.1303
B19: Subscription services | C19: 31768 | D19: 35218 | E19: 40209 | F19: 44374 | G19: 49619 | H19: =G19*(1+Assumptions!I38) -> 54749.605 | I19: =H19*(1+I20) -> 60049.366 | J19: =I19*(1+J20) -> 65441.799 | K19: =J19*(1+K20) -> 70853.836 | L19: =K19*(1+L20) -> 76465.46
B20: Subscription services growth | D20: =D19/C19-1 -> 0.10859985 | E20: =E19/D19-1 -> 0.1417173 | F20: =F19/E19-1 -> 0.10358377 | G20: =G19/F19-1 -> 0.11819985 | H20: =Assumptions!I36 -> 0.1034 | I20: =Assumptions!J36 -> 0.0968 | J20: =Assumptions!K36 -> 0.0898 | K20: =Assumptions!L36 -> 0.0827 | L20: =Assumptions!M36 -> 0.0792
B22: AWS | C22: 62202 | D22: 80096 | E22: 90757 | F22: 107556 | G22: 128725 | H22: =G22*(1+Assumptions!I38) -> 142035.16 | I22: =H22*(1+I23) -> 174547.01 | J22: =I22*(1+J23) -> 213663 | K22: =J22*(1+K23) -> 253596.61 | L22: =K22*(1+L23) -> 296429.08
B23: AWS growth | D23: =D22/C22-1 -> 0.28767564 | E23: =E22/D22-1 -> 0.13310278 | F23: =F22/E22-1 -> 0.18509867 | G23: =G22/F22-1 -> 0.1968184 | H23: =Assumptions!I42 -> 0.2443 | I23: =Assumptions!J42 -> 0.2289 | J23: =Assumptions!K42 -> 0.2241 | K23: =Assumptions!L42 -> 0.1869 | L23: =Assumptions!M42 -> 0.1689
B25: Other | C25: 2176 | D25: 4247 | E25: 4958 | F25: 5425 | G25: 5935 | H25: =G25*(1+Assumptions!I50) -> 6172.4 | I25: =H25*(1+I26) -> 6419.296 | J25: =I25*(1+J26) -> 6676.0678 | K25: =J25*(1+K26) -> 6943.1106 | L25: =K25*(1+L26) -> 7220.835
B26: Other growth | E26: =E25/D25-1 -> 0.16741229 | F26: =F25/E25-1 -> 0.094191206 | G26: =G25/F25-1 -> 0.094009217 | H26: =Assumptions!I48 -> 0.04 | I26: =Assumptions!J48 -> 0.04 | J26: =Assumptions!K48 -> 0.04 | K26: =Assumptions!L48 -> 0.04 | L26: =Assumptions!M48 -> 0.04
B28: Net sales | C28: =SUM(C25,C22,C19,C16,C13,C10,C7) -> 469822 | D28: =SUM(D25,D22,D19,D16,D13,D10,D7) -> 513983 | E28: =SUM(E25,E22,E19,E16,E13,E10,E7) -> 574785 | F28: =SUM(F25,F22,F19,F16,F13,F10,F7) -> 637959 | G28: =SUM(G25,G22,G19,G16,G13,G10,G7) -> 716924 | H28: =SUM(H25,H22,H19,H16,H13,H10,H7) -> 787751.57 | I28: =SUM(I25,I22,I19,I16,I13,I10,I7) -> 878484.96 | J28: =SUM(J25,J22,J19,J16,J13,J10,J7) -> 980198.93 | ... L28: =SUM(L25,L22,L19,L16,L13,L10,L7) -> 1198858.2
B29: change ($) | D29: =D28-C28 -> 44161 | E29: =E28-D28 -> 60802 | F29: =F28-E28 -> 63174 | G29: =G28-F28 -> 78965 | H29: =H28-G28 -> 70827.57 | I29: =I28-H28 -> 90733.393 | J29: =J28-I28 -> 101713.96 | K29: =K28-J28 -> 106438.04 | L29: =L28-K28 -> 112221.19
B31: Cost of sales | C31: 272344 | D31: 288831 | E31: 304739 | F31: 326288 | G31: 356414 | H31: =H32*H28 -> 386786.02 | I31: =I32*I28 -> 421233.54 | J31: =J32*J28 -> 452361.8 | K31: =K32*K28 -> 497897.06 | L31: =L32*L28 -> 536848.68
B32: % of revenue | C32: =C31/C28 -> 0.57967486 | D32: =D31/D28 -> 0.5619466 | E32: =E31/E28 -> 0.53017911 | F32: =F31/F28 -> 0.51145607 | G32: =G31/G28 -> 0.49714335 | H32: =Assumptions!I84 -> 0.491 | I32: =Assumptions!J84 -> 0.4795 | J32: =Assumptions!K84 -> 0.4615 | K32: =Assumptions!L84 -> 0.4582 | L32: =Assumptions!M84 -> 0.4478
B34: Gross profit | C34: =C28-C31 -> 197478 | D34: =D28-D31 -> 225152 | E34: =E28-E31 -> 270046 | F34: =F28-F31 -> 311671 | G34: =G28-G31 -> 360510 | H34: =H28-H31 -> 400965.55 | I34: =I28-I31 -> 457251.42 | J34: =J28-J31 -> 527837.12 | ... L34: =L28-L31 -> 662009.47
B36: Operating expenses
B37: Fulfillment | C37: 75111 | D37: 84299 | E37: 90619 | F37: 98505 | G37: 109074 | H37: =H28*Assumptions!I54 -> 119808.88 | I37: =I28*Assumptions!J54 -> 131286.6 | J37: =J28*Assumptions!K54 -> 143537.14 | K37: =K28*Assumptions!L54 -> 154144.61 | L37: =L28*Assumptions!M54 -> 165031.06
B38: Technology and infrastructure | C38: 56052 | D38: 73213 | E38: 85622 | F38: 88544 | G38: 108521 | H38: =H28*Assumptions!I60 -> 123755.77 | I38: =I28*Assumptions!J60 -> 140381.9 | J38: =J28*Assumptions!K60 -> 163007.08 | K38: =K28*Assumptions!L60 -> 184510.96 | L38: =L28*Assumptions!M60 -> 204525.2
B39: Sales and marketing | C39: 32551 | D39: 42238 | E39: 44370 | F39: 43907 | G39: 47129 | H39: =H28*Assumptions!I66 -> 51282.627 | I39: =I28*Assumptions!J66 -> 56662.28 | J39: =J28*Assumptions!K66 -> 61458.473 | K39: =K28*Assumptions!L66 -> 65958.864 | L39: =L28*Assumptions!M66 -> 70972.403
B40: General and administrative | C40: 8823 | D40: 11891 | E40: 11816 | F40: 11359 | G40: 11172 | H40: =H28*Assumptions!I72 -> 12288.924 | I40: =I28*Assumptions!J72 -> 14055.759 | J40: =J28*Assumptions!K72 -> 14506.944 | K40: =K28*Assumptions!L72 -> 14995.59 | L40: =L28*Assumptions!M72 -> 15705.042
B41: Other expenses | C41: 62 | D41: 1263 | E41: 767 | F41: 763 | G41: 4639 | H41: =H28*Assumptions!I78 -> 1508.14 | I41: =I28*Assumptions!J78 -> 1636.42 | J41: =J28*Assumptions!K78 -> 1965.34 | K41: =K28*Assumptions!L78 -> 2209.81 | L41: =L28*Assumptions!M78 -> 2397.7163
B43: Total operating expenses | C43: =SUM(C37:C41) -> 172599 | D43: =SUM(D37:D41) -> 212904 | E43: =SUM(E37:E41) -> 233194 | F43: =SUM(F37:F41) -> 243078 | G43: =SUM(G37:G41) -> 280535 | H43: =SUM(H37:H41) -> 308644.34 | I43: =SUM(I37:I41) -> 344022.96 | J43: =SUM(J37:J41) -> 384474.98 | ... L43: =SUM(L37:L41) -> 458631.42
B45: EBIT | C45: =C34-C43 -> 24879 | D45: =D34-D43 -> 12248 | E45: =E34-E43 -> 36852 | F45: =F34-F43 -> 68593 | G45: =G34-G43 -> 79975 | H45: =H34-H43 -> 92321.206 | I45: =I34-I43 -> 113228.47 | J45: =J34-J43 -> 143362.14 | ... L45: =L34-L43 -> 203378.05
B47: Interest income | C47: 448 | D47: 989 | E47: 2949 | F47: 4677 | G47: 4381
B48: Interest expense | C48: 1809 | D48: 2367 | E48: 3182 | F48: 2406 | G48: 2274
B49: Other income | C49: =14651-19 -> 14632 | D49: =-16266-540 -> -16806 | E49: =1115-177 -> 938 | F49: =-1829-421 -> -2250 | G49: =15320-91 -> 15229
B51: EBT | C51: =C45+C47-C48+C49 -> 38150 | D51: =D45+D47-D48+D49 -> -5936 | E51: =E45+E47-E48+E49 -> 37557 | F51: =F45+F47-F48+F49 -> 68614 | G51: =G45+G47-G48+G49 -> 97311 | H51: =H45+H47-H48+H49 -> 92321.206 | I51: =I45+I47-I48+I49 -> 113228.47 | J51: =J45+J47-J48+J49 -> 143362.14 | ... L51: =L45+L47-L48+L49 -> 203378.05
B52: Taxes | C52: 4791 | D52: -3217 | E52: 7120 | F52: 9265 | G52: 19087 | H52: =H51*Assumptions!$D$132 -> 14917.648 | I52: =I51*Assumptions!$D$132 -> 18295.931 | J52: =J51*Assumptions!$D$132 -> 23165.057 | K52: =K51*Assumptions!$D$132 -> 26971.647 | L52: =L51*Assumptions!$D$132 -> 32862.68
B54: Net income | C54: =C51-C52 -> 33359 | D54: =D51-D52 -> -2719 | E54: =E51-E52 -> 30437 | F54: =F51-F52 -> 59349 | G54: =G51-G52 -> 78224 | H54: =H51-H52 -> 77403.557 | I54: =I51-I52 -> 94932.535 | J54: =J51-J52 -> 120197.09 | ... L54: =L51-L52 -> 170515.37
B56: Capital Expenditures and Depreciation:
B58: Gross property and equipment | C58: 238800 | D58: 283730 | E58: 324288 | F58: 394055 | G58: 534098 | H58: =G58+G62 -> 662418 | I58: =H58+H62 -> 851478.38 | J58: =I58+I62 -> 1027175.4 | K58: =J58+J62 -> 1203611.2 | L58: =K58+K62 -> 1366606.7 | M58: =_xlfn.FORMULATEXT(L58) -> =K58+K62
B59: Total accumulated depreciation and amortization | C59: 78519 | D59: 97015 | E59: 120111 | F59: 141390 | G59: 177073 | H59: =G58*Assumptions!I104 -> 186934.3 | I59: =H58*Assumptions!J104 -> 231846.3 | J59: =I58*Assumptions!K104 -> 298017.43 | K59: =J58*Assumptions!L104 -> 359511.38 | L59: =K58*Assumptions!M104 -> 421263.91 | M59: =_xlfn.FORMULATEXT(L59) -> =K58*Assumptions!M104
B60: Total property and equipment, net | C60: =C58-C59 -> 160281 | D60: =D58-D59 -> 186715 | E60: =E58-E59 -> 204177 | F60: =F58-F59 -> 252665 | G60: =G58-G59 -> 357025 | H60: =H58-H59 -> 475483.7 | I60: =I58-I59 -> 619632.08 | J60: =J58-J59 -> 729157.94 | ... L60: =L58-L59 -> 945342.81 | M60: =_xlfn.FORMULATEXT(L60) -> =L58-L59
B62: Capital expenditures | C62: =61053-5657 -> 55396 | D62: =63645-5324 -> 58321 | E62: =52729-4596 -> 48133 | F62: =82999-5341 -> 77658 | G62: =131819-3499 -> 128320 | H62: =H28*Assumptions!I98 -> 189060.38 | I62: =I28*Assumptions!J98 -> 175696.99 | J62: =J28*Assumptions!K98 -> 176435.81 | K62: =K28*Assumptions!L98 -> 162995.55 | L62: =L28*Assumptions!M98 -> 179828.72 | M62: =_xlfn.FORMULATEXT(L62) -> =L28*Assumptions!M98
B63: Depreciation | C63: 34433 | D63: 41921 | E63: 48663 | F63: 52795 | G63: 65756 | H63: =G58*H65 -> 90360.455 | I63: =H58*I65 -> 112070.05 | J63: =I58*J65 -> 144055.91 | K63: =J58*K65 -> 173780.91 | L63: =K58*L65 -> 203630.9
B65: Depreciation / Prior Yr PP&E | D65: =D63/C58 -> 0.17554858 | E65: =E63/D58 -> 0.17151165 | F65: =F63/E58 -> 0.16280282 | G65: =G63/F58 -> 0.16687011 | H65: =AVERAGE($D$65:$G$65) -> 0.16918329 | I65: =AVERAGE($D$65:$G$65) -> 0.16918329 | J65: =AVERAGE($D$65:$G$65) -> 0.16918329 | K65: =AVERAGE($D$65:$G$65) -> 0.16918329 | L65: =AVERAGE($D$65:$G$65) -> 0.16918329
B66: (FCInv-NCC)/D(Sales) | D66: =(D62-D63)/D29 -> 0.3713684 | E66: =(E62-E63)/E29 -> -0.0087168185 | F66: =(F62-F63)/F29 -> 0.39356381 | G66: =(G62-G63)/G29 -> 0.79230039 | H66: =(H62-H63)/H29 -> 1.393524 | I66: =(I62-I63)/I29 -> 0.70125161 | J66: =(J62-J63)/J29 -> 0.31834268 | K66: =(K62-K63)/K29 -> -0.10132994 | L66: =(L62-L63)/L29 -> -0.21210052
B69: Changes in Net Working Capital:
B71: Current assets
B72: Accounts receivable | C72: 32891 | D72: 42360 | E72: 52253 | F72: 55451 | G72: 67729 | H72: =H87*H28 -> 72709.47 | I72: =I87*I28 -> 80381.374 | J72: =J87*J28 -> 92530.779 | K72: =K87*K28 -> 97797.327 | L72: =L87*L28 -> 106698.38
B73: Inventory | C73: 32640 | D73: 34405 | E73: 33318 | F73: 34214 | G73: 38325 | H73: =H88*H28 -> 41672.058 | I73: =I88*I28 -> 45066.279 | J73: =J88*J28 -> 49304.006 | K73: =K88*K28 -> 53245.211 | L73: =L88*L28 -> 57305.42
B75: Total current assets | C75: =C72+C73 -> 65531 | D75: =D72+D73 -> 76765 | E75: =E72+E73 -> 85571 | F75: =F72+F73 -> 89665 | G75: =G72+G73 -> 106054 | H75: =H72+H73 -> 114381.53 | I75: =I72+I73 -> 125447.65 | J75: =J72+J73 -> 141834.78 | ... L75: =L72+L73 -> 164003.8
B77: Current liabilities
B78: Accounts payable | C78: 78664 | D78: 79600 | E78: 84891 | F78: 94363 | G78: 121909 | H78: =H90*H43 -> 120340.43 | I78: =I90*I43 -> 129765.46 | J78: =J90*J43 -> 132144.05 | K78: =K90*K43 -> 148143.12 | L78: =L90*L43 -> 156943.67
B79: Accrued expenses | C79: 51775 | D79: 62566 | E79: 64709 | F79: 66965 | G79: 75520 | H79: =H91*H43 -> 81050.005 | I79: =I91*I43 -> 85730.521 | J79: =J91*J43 -> 94042.58 | K79: =K91*K43 -> 98958.932 | L79: =L91*L43 -> 105301.77
C81: =C78+C79 -> 130439 | D81: =D78+D79 -> 142166 | E81: =E78+E79 -> 149600 | F81: =F78+F79 -> 161328 | G81: =G78+G79 -> 197429 | H81: =H78+H79 -> 201390.43 | I81: =I78+I79 -> 215495.98 | J81: =J78+J79 -> 226186.63 | ... L81: =L78+L79 -> 262245.45
B82: NWC | C82: =C75-C81 -> -64908 | D82: =D75-D81 -> -65401 | E82: =E75-E81 -> -64029 | F82: =F75-F81 -> -71663 | G82: =G75-G81 -> -91375
B83: NWCInv | D83: =D82-C82 -> -493 | E83: =E82-D82 -> 1372 | F83: =F82-E82 -> -7634 | G83: =G82-F82 -> -19712
B84: WCInv/D(Sales) | D84: =D83/D29 -> -0.011163696 | E84: =E83/E29 -> 0.022565047 | F84: =F83/F29 -> -0.12084085 | G84: =G83/G29 -> -0.24962958
B86: Projection:
B87: Accounts receivable - % of revenue | C87: =C72/C28 -> 0.070007364 | D87: =D72/D28 -> 0.082415177 | E87: =E72/E28 -> 0.090908775 | F87: =F72/F28 -> 0.086919379 | G87: =G72/G28 -> 0.094471659 | H87: =Assumptions!I110 -> 0.0923 | I87: =Assumptions!J110 -> 0.0915 | J87: =Assumptions!K110 -> 0.0944 | K87: =Assumptions!L110 -> 0.09 | L87: =Assumptions!M110 -> 0.089
B88: Inventory - % of revenue | C88: =C73/C28 -> 0.06947312 | D88: =D73/D28 -> 0.066938012 | E88: =E73/E28 -> 0.057966022 | F88: =F73/F28 -> 0.053630406 | G88: =G73/G28 -> 0.053457549 | H88: =Assumptions!I116 -> 0.0529 | I88: =Assumptions!J116 -> 0.0513 | J88: =Assumptions!K116 -> 0.0503 | K88: =Assumptions!L116 -> 0.049 | L88: =Assumptions!M116 -> 0.0478
B90: Accounts payable - % of operating expenses | C90: =C78/C43 -> 0.45576162 | D90: =D78/D43 -> 0.37387743 | E90: =E78/E43 -> 0.36403595 | F90: =F78/F43 -> 0.3882005 | G90: =G78/G43 -> 0.43455897 | H90: =Assumptions!I122 -> 0.3899 | I90: =Assumptions!J122 -> 0.3772 | J90: =Assumptions!K122 -> 0.3437 | K90: =Assumptions!L122 -> 0.3512 | L90: =Assumptions!M122 -> 0.3422
B91: Accrued expenses - % of operating expenses | C91: =C79/C43 -> 0.29997277 | D91: =D79/D43 -> 0.29386954 | E91: =E79/E43 -> 0.27748999 | F91: =F79/F43 -> 0.2754877 | G91: =G79/G43 -> 0.26919992 | H91: =Assumptions!I128 -> 0.2626 | I91: =Assumptions!J128 -> 0.2492 | J91: =Assumptions!K128 -> 0.2446 | K91: =Assumptions!L128 -> 0.2346 | L91: =Assumptions!M128 -> 0.2296
B93: Change in NWC | D93: =(D75-C75)-(D81-C81) -> -493 | E93: =(E75-D75)-(E81-D81) -> 1372 | F93: =(F75-E75)-(F81-E81) -> -7634 | G93: =(G75-F75)-(G81-F81) -> -19712 | H93: =(H75-G75)-(H81-G81) -> 4366.0939 | I93: =(I75-H75)-(I81-H81) -> -3039.4212 | J93: =(J75-I75)-(J81-I81) -> 5696.4822 | K93: =(K75-J75)-(K81-J81) -> -11707.674 | L93: =(L75-K75)-(L81-K81) -> -2182.133

Sheet FCF Calculation
G2: ="CURRENTLY VIEWING "&CHOOSE(Assumptions!$D$3,"DOWNSIDE","BASE","UPSIDE")&" CASE" -> CURRENTLY VIEWING BASE CASE
B3: Free Cash Flow Calculation | C3: Expected
B4: USD ($) in millions | C4: 2026 | D4: =C4+1 -> 2027 | E4: =D4+1 -> 2028 | F4: =E4+1 -> 2029 | G4: =F4+1 -> 2030
B6: EBIT | C6: ='FCF Components'!H45 -> 92321.206 | D6: ='FCF Components'!I45 -> 113228.47 | E6: ='FCF Components'!J45 -> 143362.14 | F6: ='FCF Components'!K45 -> 166920.08 | G6: ='FCF Components'!L45 -> 203378.05
B7: (1-Tax Rate) | C7: ='WACC Calculation'!$K$9 -> 0.8384158 | D7: ='WACC Calculation'!$K$9 -> 0.8384158 | E7: ='WACC Calculation'!$K$9 -> 0.8384158 | F7: ='WACC Calculation'!$K$9 -> 0.8384158 | G7: ='WACC Calculation'!$K$9 -> 0.8384158
B8: EBIT(1-Tax Rate) | C8: =C6*C7 -> 77403.557 | D8: =D6*D7 -> 94932.535 | E8: =E6*E7 -> 120197.09 | F8: =F6*F7 -> 139948.43 | G8: =G6*G7 -> 170515.37
B9: Depreciation | C9: ='FCF Components'!H63 -> 90360.455 | D9: ='FCF Components'!I63 -> 112070.05 | E9: ='FCF Components'!J63 -> 144055.91 | F9: ='FCF Components'!K63 -> 173780.91 | G9: ='FCF Components'!L63 -> 203630.9
B10: Capital Expenditures | C10: ='FCF Components'!H62 -> 189060.38 | D10: ='FCF Components'!I62 -> 175696.99 | E10: ='FCF Components'!J62 -> 176435.81 | F10: ='FCF Components'!K62 -> 162995.55 | G10: ='FCF Components'!L62 -> 179828.72
B11: Change in NWC | C11: ='FCF Components'!H93 -> 4366.0939 | D11: ='FCF Components'!I93 -> -3039.4212 | E11: ='FCF Components'!J93 -> 5696.4822 | F11: ='FCF Components'!K93 -> -11707.674 | G11: ='FCF Components'!L93 -> -2182.133
B12: Free Cash Flow | C12: =C8+C9-C10-C11 -> -25662.458 | D12: =D8+D9-D10-D11 -> 34345.019 | E12: =E8+E9-E10-E11 -> 82120.708 | F12: =F8+F9-F10-F11 -> 162441.46 | G12: =G8+G9-G10-G11 -> 196499.68

Sheet WACC Calculation
B3: WACC Calculation | D3: Cost of Equity (CAPM) | G3: Cost of debt | J3: WACC
D4: Risk-free rate | E4: 0.04229 | G4: Interest expense | H4: ='FCF Components'!G48 -> 2274 | J4: Cost of equity | K4: =E7 -> 0.103838
D5: Equity beta | E5: 1.38 | G5: Debt | H5: 65648 | J5: Weight of equity | K5: =F12 -> 0.86229031
D6: Expected market return | E6: =E4+4.46% -> 0.08689 | G6: Cost of debt | H6: =H4/H5 -> 0.034639288
D7: Cost of equity | E7: =E5*(E6-E4)+E4 -> 0.103838 | J7: Cost of debt | K7: 0.06
J8: Weight of debt | K8: =F13 -> 0.13770969
J9: (1-Tax Rate) | K9: =1-Assumptions!D132 -> 0.8384158
D11: Weight of Debt and Equity | E11: Total | F11: Weight | J11: WACC | K11: =K4*K5+K7*K8*K9 -> 0.09646598
D12: Total Equity | E12: 411065 | F12: =E12/(E12+E13) -> 0.86229031
D13: Total Long Term Debt(Debt) | E13: =H5 -> 65648 | F13: =1-F12 -> 0.13770969

Sheet DCF
G2: ="CURRENTLY VIEWING "&CHOOSE(Assumptions!$D$3,"DOWNSIDE","BASE","UPSIDE")&" CASE" -> CURRENTLY VIEWING BASE CASE
B3: DCF | C3: 2026 | D3: =C3+1 -> 2027 | E3: =D3+1 -> 2028 | F3: =E3+1 -> 2029 | G3: =F3+1 -> 2030 | I3: Terminal Assumptions
B4: FCF | C4: ='FCF Calculation'!C12 -> -25662.458 | D4: ='FCF Calculation'!D12 -> 34345.019 | E4: ='FCF Calculation'!E12 -> 82120.708 | F4: ='FCF Calculation'!F12 -> 162441.46 | G4: ='FCF Calculation'!G12 -> 196499.68 | I4: Valuation Date | J4: =TODAY() -> 46129
B5: Discount Factor | C5: =(1/(1+($J$7))) -> 0.912021 | D5: =(C5/(1+$J$7)) -> 0.83178231 | E5: =(D5/(1+$J$7)) -> 0.75860293 | F5: =(E5/(1+$J$7)) -> 0.6918618 | G5: =(F5/(1+$J$7)) -> 0.63099249 | I5: Fiscal Year End | J5: 46387
B6: Present Value | C6: =C4*C5 -> -23404.701 | D6: =D4*D5 -> 28567.579 | E6: =E4*E5 -> 62297.01 | F6: =F4*F5 -> 112387.04 | G6: =G4*G5 -> 123989.82
I7: WACC | J7: ='WACC Calculation'!K11 -> 0.09646598
I8: Terminal Growth Rate | J8: 0.03
C9: Growth Rate YoY
B10: WACC | C10: =D10-0.005 -> 0.02 | D10: =E10-0.005 -> 0.025 | E10: =J8 -> 0.03 | F10: =E10+0.005 -> 0.035 | G10: =F10+0.005 -> 0.04 | I10: Current Valuation
B11: =B12-0.01 -> 0.07646598 | C11: =(($C$4*1/(1+$B11)+$D$4*1/(1+$B11)^2+$E$4*1/(1+$B11)^3+$F$4*1/(1+$B11)^4+$G$4*1/(1+$B11)^5+(($G$4*(1+C$10))/($B11-C$10))*1/(1+$B11)^5)-$J$15+$J$16)/$J$18 -> 261.33451 | D11: =(($C$4*1/(1+$B11)+$D$4*1/(1+$B11)^2+$E$4*1/(1+$B11)^3+$F$4*1/(1+$B11)^4+$G$4*1/(1+$B11)^5+(($G$4*(1+D$10))/($B11-D$10))*1/(1+$B11)^5)-$J$15+$J$16)/$J$18 -> 284.78893 | E11: =(($C$4*1/(1+$B11)+$D$4*1/(1+$B11)^2+$E$4*1/(1+$B11)^3+$F$4*1/(1+$B11)^4+$G$4*1/(1+$B11)^5+(($G$4*(1+E$10))/($B11-E$10))*1/(1+$B11)^5)-$J$15+$J$16)/$J$18 -> 313.291 | F11: =(($C$4*1/(1+$B11)+$D$4*1/(1+$B11)^2+$E$4*1/(1+$B11)^3+$F$4*1/(1+$B11)^4+$G$4*1/(1+$B11)^5+(($G$4*(1+F$10))/($B11-F$10))*1/(1+$B11)^5)-$J$15+$J$16)/$J$18 -> 348.66668 | G11: =(($C$4*1/(1+$B11)+$D$4*1/(1+$B11)^2+$E$4*1/(1+$B11)^3+$F$4*1/(1+$B11)^4+$G$4*1/(1+$B11)^5+(($G$4*(1+G$10))/($B11-G$10))*1/(1+$B11)^5)-$J$15+$J$16)/$J$18 -> 393.74336 | I11: Terminal Value | J11: =(G4*(1+J8))/(J7-J8) -> 3045086.6
B12: =B13-0.01 -> 0.08646598 | C12: =(($C$4*1/(1+$B12)+$D$4*1/(1+$B12)^2+$E$4*1/(1+$B12)^3+$F$4*1/(1+$B12)^4+$G$4*1/(1+$B12)^5+(($G$4*(1+C$10))/($B12-C$10))*1/(1+$B12)^5)-$J$15+$J$16)/$J$18 -> 216.95747 | D12: =(($C$4*1/(1+$B12)+$D$4*1/(1+$B12)^2+$E$4*1/(1+$B12)^3+$F$4*1/(1+$B12)^4+$G$4*1/(1+$B12)^5+(($G$4*(1+D$10))/($B12-D$10))*1/(1+$B12)^5)-$J$15+$J$16)/$J$18 -> 233.03555 | E12: =(($C$4*1/(1+$B12)+$D$4*1/(1+$B12)^2+$E$4*1/(1+$B12)^3+$F$4*1/(1+$B12)^4+$G$4*1/(1+$B12)^5+(($G$4*(1+E$10))/($B12-E$10))*1/(1+$B12)^5)-$J$15+$J$16)/$J$18 -> 251.96103 | F12: =(($C$4*1/(1+$B12)+$D$4*1/(1+$B12)^2+$E$4*1/(1+$B12)^3+$F$4*1/(1+$B12)^4+$G$4*1/(1+$B12)^5+(($G$4*(1+F$10))/($B12-F$10))*1/(1+$B12)^5)-$J$15+$J$16)/$J$18 -> 274.56378 | G12: =(($C$4*1/(1+$B12)+$D$4*1/(1+$B12)^2+$E$4*1/(1+$B12)^3+$F$4*1/(1+$B12)^4+$G$4*1/(1+$B12)^5+(($G$4*(1+G$10))/($B12-G$10))*1/(1+$B12)^5)-$J$15+$J$16)/$J$18 -> 302.03091 | I12: PV of Terminal Value | J12: =J11*G5 -> 1921426.8
B13: =J7 -> 0.09646598 | C13: =(($C$4*1/(1+$B13)+$D$4*1/(1+$B13)^2+$E$4*1/(1+$B13)^3+$F$4*1/(1+$B13)^4+$G$4*1/(1+$B13)^5+(($G$4*(1+C$10))/($B13-C$10))*1/(1+$B13)^5)-$J$15+$J$16)/$J$18 -> 184.34528 | D13: =(($C$4*1/(1+$B13)+$D$4*1/(1+$B13)^2+$E$4*1/(1+$B13)^3+$F$4*1/(1+$B13)^4+$G$4*1/(1+$B13)^5+(($G$4*(1+D$10))/($B13-D$10))*1/(1+$B13)^5)-$J$15+$J$16)/$J$18 -> 195.93265 | E13: =(($C$4*1/(1+$B13)+$D$4*1/(1+$B13)^2+$E$4*1/(1+$B13)^3+$F$4*1/(1+$B13)^4+$G$4*1/(1+$B13)^5+(($G$4*(1+E$10))/($B13-E$10))*1/(1+$B13)^5)-$J$15+$J$16)/$J$18 -> 209.26337 | F13: =(($C$4*1/(1+$B13)+$D$4*1/(1+$B13)^2+$E$4*1/(1+$B13)^3+$F$4*1/(1+$B13)^4+$G$4*1/(1+$B13)^5+(($G$4*(1+F$10))/($B13-F$10))*1/(1+$B13)^5)-$J$15+$J$16)/$J$18 -> 224.76289 | G13: =(($C$4*1/(1+$B13)+$D$4*1/(1+$B13)^2+$E$4*1/(1+$B13)^3+$F$4*1/(1+$B13)^4+$G$4*1/(1+$B13)^5+(($G$4*(1+G$10))/($B13-G$10))*1/(1+$B13)^5)-$J$15+$J$16)/$J$18 -> 243.00734 | I13: PV of Present Value | J13: =SUM(C6:G6) -> 303836.75
B14: =B13+0.01 -> 0.10646598 | C14: =(($C$4*1/(1+$B14)+$D$4*1/(1+$B14)^2+$E$4*1/(1+$B14)^3+$F$4*1/(1+$B14)^4+$G$4*1/(1+$B14)^5+(($G$4*(1+C$10))/($B14-C$10))*1/(1+$B14)^5)-$J$15+$J$16)/$J$18 -> 159.40982 | D14: =(($C$4*1/(1+$B14)+$D$4*1/(1+$B14)^2+$E$4*1/(1+$B14)^3+$F$4*1/(1+$B14)^4+$G$4*1/(1+$B14)^5+(($G$4*(1+D$10))/($B14-D$10))*1/(1+$B14)^5)-$J$15+$J$16)/$J$18 -> 168.07863 | E14: =(($C$4*1/(1+$B14)+$D$4*1/(1+$B14)^2+$E$4*1/(1+$B14)^3+$F$4*1/(1+$B14)^4+$G$4*1/(1+$B14)^5+(($G$4*(1+E$10))/($B14-E$10))*1/(1+$B14)^5)-$J$15+$J$16)/$J$18 -> 177.88111 | F14: =(($C$4*1/(1+$B14)+$D$4*1/(1+$B14)^2+$E$4*1/(1+$B14)^3+$F$4*1/(1+$B14)^4+$G$4*1/(1+$B14)^5+(($G$4*(1+F$10))/($B14-F$10))*1/(1+$B14)^5)-$J$15+$J$16)/$J$18 -> 189.05523 | G14: =(($C$4*1/(1+$B14)+$D$4*1/(1+$B14)^2+$E$4*1/(1+$B14)^3+$F$4*1/(1+$B14)^4+$G$4*1/(1+$B14)^5+(($G$4*(1+G$10))/($B14-G$10))*1/(1+$B14)^5)-$J$15+$J$16)/$J$18 -> 201.91052 | I14: PV of EV | J14: =J13+J12 -> 2225263.6
B15: =B14+0.01 -> 0.11646598 | C15: =(($C$4*1/(1+$B15)+$D$4*1/(1+$B15)^2+$E$4*1/(1+$B15)^3+$F$4*1/(1+$B15)^4+$G$4*1/(1+$B15)^5+(($G$4*(1+C$10))/($B15-C$10))*1/(1+$B15)^5)-$J$15+$J$16)/$J$18 -> 139.75841 | D15: =(($C$4*1/(1+$B15)+$D$4*1/(1+$B15)^2+$E$4*1/(1+$B15)^3+$F$4*1/(1+$B15)^4+$G$4*1/(1+$B15)^5+(($G$4*(1+D$10))/($B15-D$10))*1/(1+$B15)^5)-$J$15+$J$16)/$J$18 -> 146.43443 | E15: =(($C$4*1/(1+$B15)+$D$4*1/(1+$B15)^2+$E$4*1/(1+$B15)^3+$F$4*1/(1+$B15)^4+$G$4*1/(1+$B15)^5+(($G$4*(1+E$10))/($B15-E$10))*1/(1+$B15)^5)-$J$15+$J$16)/$J$18 -> 153.88254 | F15: =(($C$4*1/(1+$B15)+$D$4*1/(1+$B15)^2+$E$4*1/(1+$B15)^3+$F$4*1/(1+$B15)^4+$G$4*1/(1+$B15)^5+(($G$4*(1+F$10))/($B15-F$10))*1/(1+$B15)^5)-$J$15+$J$16)/$J$18 -> 162.24491 | G15: =(($C$4*1/(1+$B15)+$D$4*1/(1+$B15)^2+$E$4*1/(1+$B15)^3+$F$4*1/(1+$B15)^4+$G$4*1/(1+$B15)^5+(($G$4*(1+G$10))/($B15-G$10))*1/(1+$B15)^5)-$J$15+$J$16)/$J$18 -> 171.70089 | I15: - Debt | J15: ='WACC Calculation'!H5 -> 65648
I16: + Cash | J16: 86810
I17: PV of Equity | J17: =J14-J15+J16 -> 2246425.6
I18: Shares | J18: 10734.92
I19: Price per share | J19: =J17/J18 -> 209.26337
F23: Case Probabilities | I23: Base | J23: 209.26337
F24: Downside | G24: 0.1 | I24: Upside | J24: 264.96069
F25: Base | G25: 0.6 | I25: Downside | J25: 159.17312
F26: Upside | G26: 0.3 | I26: Weighted Avg. | J26: =(J23*DCF!$G$25)+(J24*DCF!$G$26)+(J25*DCF!$G$24) -> 220.96354

Sheet Comps
A1: ($ in billions)
A2: Company | C2: Price | D2: Shares Outstanding | E2: Total Debt | F2: Total Cash | G2: Enterprise Value | J2: EV-based multiples
A3: Apple(AAPL) | C3: =C39 -> 248.8 | D3: 14.78 | E3: 90.51 | F3: 45.32 | G3: =C3*D3+E3-F3 -> 3722.454 | J3: Multiple | K3: Amazon Metric | L3: Avg. comp multiple | M3: Implied EV ($B) | N3: Equity Value ($B) | O3: Implied Price/Share
A4: Alphabet(GOOGL) | C4: =C40 -> 274.34 | D4: 12.07 | E4: 59.29 | F4: 30.71 | G4: =C4*D4+E4-F4 -> 3339.8638 | J4: EV/Sales | K4: ='FCF Components'!G28/1000 -> 716.924 | L4: =G18 -> 5.7256333 | M4: =L4*K4 -> 4104.8439 | N4: =M4-$L$12+$L$13 -> 4126.0059 | O4: =N4/$L$15 -> 385.96875
A5: Meta(META) | C5: =C41 -> 525.72 | D5: 2.53 | E5: 83.9 | F5: 35.87 | G5: =C5*D5+E5-F5 -> 1378.1016 | J5: EV/EBITDA | K5: ='FCF Components'!G45/1000 + ('FCF Components'!G63/1000) -> 145.731 | L5: =G27 -> 16.466421 | M5: =L5*K5 -> 2399.668 | N5: =M5-$L$12+$L$13 -> 2420.83 | O5: =N5/$L$15 -> 226.45744
A6: Microsoft(MSFT) | C6: =C42 -> 356.77 | D6: 7.43 | E6: 57.61 | F6: 24.3 | G6: =C6*D6+E6-F6 -> 2684.1111 | J6: EV/FCF* | K6: 24.2 | L6: =G36 -> 23.908474 | M6: =L6*K6 -> 578.58508 | N6: =M6-$L$12+$L$13 -> 599.74708 | O6: =N6/$L$15 -> 56.103562
A7: Walmart(WMT) | C7: =C43 -> 122.89 | D7: 7.97 | E7: 67.1 | F7: 10.73 | G7: =C7*D7+E7-F7 -> 1035.8033
A8: Alibaba(BABA) | C8: =C44 -> 122.69 | D8: 2.39 | E8: 262.74 | F8: 128.17 | G8: =C8*D8+E8-F8 -> 427.7991 | H8: (CNY) | J8: Price-based multiple
J9: Multiple | K9: Amazon Metric | L9: Avg. comp multiple | M9: Implied EV ($B) | N9: Implied Price/Share
J10: P/E | K10: ='FCF Components'!G54/1000/L15 -> 7.317493 | L10: =G45 -> 24.77388 | M10: =L10*K10 -> 181.2827 | N10: =L10*K10 -> 181.2827
A11: Company | C11: Enterprise Value | E11: Sales | G11: EV/ Sales | J11: Average EV of all comps | L11: =AVERAGE(M4:M6) -> 2361.0324
A12: Apple(AAPL) | C12: =G3 -> 3722.454 | E12: 435.62 | G12: =C12/E12 -> 8.5451862 | J12: Debt | L12: ='WACC Calculation'!H5/1000 -> 65.648
A13: Alphabet(GOOGL) | C13: =G4 -> 3339.8638 | E13: 402.84 | G13: =C13/E13 -> 8.2907949 | J13: Cash | L13: 86.81
A14: Meta(META) | C14: =G5 -> 1378.1016 | E14: 200.97 | G14: =C14/E14 -> 6.8572503 | J14: Equity Value | L14: =L11-L12+L13 -> 2382.1944
A15: Microsoft(MSFT) | C15: =G6 -> 2684.1111 | E15: 305.45 | G15: =C15/E15 -> 8.7873992 | J15: Shares Outstanding | L15: =10.69 -> 10.69
A16: Walmart(WMT) | C16: =G7 -> 1035.8033 | E16: 713.16 | G16: =C16/E16 -> 1.4524136 | J16: Price per Share (EV Multiples) | L16: =L14/L15 -> 222.84325
A17: Alibaba(BABA) | C17: =G8 -> 427.7991 | E17: 1016.74 | G17: =C17/E17 -> 0.42075565 | H17: (CNY) | J17: Weighted Average | L17: =L16*0.75+N10*0.25 -> 212.45311
A18: Average EV/Sales | G18: =AVERAGE(G12:G17) -> 5.7256333
A20: Company | C20: Enterprise Value | E20: EBITDA | G20: EV/ EBITDA
A21: Apple(AAPL) | C21: =G3 -> 3722.454 | E21: 152.98 | G21: =C21/E21 -> 24.332945
A22: Alphabet(GOOGL) | C22: =G4 -> 3339.8638 | E22: 176.36 | G22: =C22/E22 -> 18.937763
A23: Meta(META) | C23: =G5 -> 1378.1016 | E23: 103.59 | G23: =C23/E23 -> 13.303423
A24: Microsoft(MSFT) | C24: =G6 -> 2684.1111 | E24: 183.29 | G24: =C24/E24 -> 14.644067
A25: Walmart(WMT) | C25: =G7 -> 1035.8033 | E25: 46.1 | G25: =C25/E25 -> 22.468618
A26: Alibaba(BABA) | C26: =G8 -> 427.7991 | E26: 83.69 | G26: =C26/E26 -> 5.1117111 | H26: (CNY)
A27: Average EV/EBITDA | G27: =AVERAGE(G21:G26) -> 16.466421
A29: Company | C29: Enterprise Value | E29: FCF | G29: EV/ FCF
A30: Apple(AAPL) | C30: =G3 -> 3722.454 | E30: 132.02 | G30: =C30/E30 -> 28.196137
A31: Alphabet(GOOGL) | C31: =G4 -> 3339.8638 | E31: 72.65 | G31: =C31/E31 -> 45.971972
A32: Meta(META) | C32: =G5 -> 1378.1016 | E32: 46.99 | G32: =C32/E32 -> 29.327551
A33: Microsoft(MSFT) | C33: =G6 -> 2684.1111 | E33: 81.92 | G33: =C33/E33 -> 32.765028
A34: Walmart(WMT) | C34: =G7 -> 1035.8033 | E34: 390.2 | G34: =C34/E34 -> 2.6545446
A35: Alibaba(BABA) | C35: =G8 -> 427.7991 | E35: 94.32 | G35: =C35/E35 -> 4.5356139 | H35: (CNY)
A36: Average EV/CF | G36: =AVERAGE(G30:G35) -> 23.908474
A38: Company | C38: Price | E38: EPS | G38: P/E
A39: Apple(AAPL) | C39: 248.8 | E39: 7.92 | G39: =C39/E39 -> 31.414141
A40: Alphabet(GOOGL) | C40: 274.34 | E40: 10.91 | G40: =C40/E40 -> 25.145738
A41: Meta(META) | C41: 525.72 | E41: 23.98 | G41: =C41/E41 -> 21.923269
A42: Microsoft(MSFT) | C42: 356.77 | E42: 16.04 | G42: =C42/E42 -> 22.242519
A43: Walmart(WMT) | C43: 122.89 | E43: 2.74 | G43: =C43/E43 -> 44.850365
A44: Alibaba(BABA) | C44: 122.69 | E44: 40 | G44: =C44/E44 -> 3.06725 | H44: (CNY)
A45: Average P/E | G45: =AVERAGE(G39:G44) -> 24.77388
